mdhub/__init__.py
mdhub/cli.py
mdhub/converter.py
mdhub/models/dark.css
mdhub/models/light.css
mdhub-0.1.1.dist-info/METADATA
mdhub-0.1.1.dist-info/WHEEL
mdhub-0.1.1.dist-info/entry_points.txt
mdhub-0.1.1.dist-info/top_level.txt
mdhub-0.1.1.dist-info/RECORD
