Metadata-Version: 2.1
Name: mdhub
Version: 0.1.1
Summary: Convert Markdown files to styled HTML with a GitHub-like appearance. Easily switch between light and dark modes.
Author: GlizzyKingDreko
Author-email: glizzykingdreko@protonmail.com
Requires-Dist: beautifulsoup4
Requires-Dist: chardet
Requires-Dist: mistune
Requires-Dist: Pygments
